{"player":1,"street":0,"children":2,"sequence":[{"player":0,"type":"R","amount":10168200,"street":0},{"player":1,"type":"C","amount":10168200,"street":0},{"player":2,"type":"C","amount":8611700,"street":0},{"player":3,"type":"R","amount":10715900,"street":0},{"player":4,"type":"R","amount":12389700,"street":0},{"player":5,"type":"F","amount":0,"street":0}],"actions":[{"type":"F","amount":0},{"type":"C","amount":1122800}],"hands":{"22":{"weight":0.0,"played":[1.0E-4,0.9999],"evs":[0.0,7.70984]},"32o":{"weight":0.0,"played":[1.0E-4,0.9999],"evs":[0.0,6.14463]},"42o":{"weight":0.0,"played":[2.0E-4,0.9998],"evs":[0.0,5.52527]},"52o":{"weight":0.0,"played":[0.0,1.0],"evs":[0.0,5.95548]},"62o":{"weight":0.0,"played":[0.0,1.0],"evs":[0.0,4.67492]},"72o":{"weight":0.0,"played":[6.0E-4,0.9994],"evs":[0.0,4.84924]},"82o":{"weight":0.0,"played":[0.0,1.0],"evs":[0.0,5.38347]},"92o":{"weight":0.0,"played":[0.0,1.0],"evs":[0.0,3.16927]},"T2o":{"weight":0.0,"played":[0.0,1.0],"evs":[0.0,4.24913]},"J2o":{"weight":0.0,"played":[0.0,1.0],"evs":[0.0,4.61635]},"Q2o":{"weight":0.0,"played":[0.0,1.0],"evs":[0.0,4.7722]},"K2o":{"weight":0.0,"played":[0.0,1.0],"evs":[0.0,4.66078]},"A2o":{"weight":0.0,"played":[1.0E-4,0.9999],"evs":[0.0,4.5679]},"32s":{"weight":0.0,"played":[6.0E-4,0.9994],"evs":[0.0,6.67323]},"33":{"weight":0.0,"played":[0.0,1.0],"evs":[0.0,7.33972]},"43o":{"weight":0.0,"played":[0.0,1.0],"evs":[0.0,5.90037]},"53o":{"weight":0.0,"played":[0.0,1.0],"evs":[0.0,6.74814]},"63o":{"weight":0.0,"played":[1.0E-4,0.9999],"evs":[0.0,5.90763]},"73o":{"weight":0.0,"played":[0.0,1.0],"evs":[0.0,4.86563]},"83o":{"weight":0.0,"played":[0.0,1.0],"evs":[0.0,4.32673]},"93o":{"weight":0.0,"played":[1.0E-4,0.9999],"evs":[0.0,4.22158]},"T3o":{"weight":0.0,"played":[0.0,1.0],"evs":[0.0,4.37085]},"J3o":{"weight":0.0,"played":[0.0,1.0],"evs":[0.0,4.53254]},"Q3o":{"weight":0.0,"played":[1.0E-4,0.9999],"evs":[0.0,5.14059]},"K3o":{"weight":0.0,"played":[0.0,1.0],"evs":[0.0,4.85985]},"A3o":{"weight":0.0,"played":[0.0,1.0],"evs":[0.0,5.84203]},"42s":{"weight":0.0,"played":[0.0,1.0],"evs":[0.0,8.11548]},"43s":{"weight":0.0,"played":[2.0E-4,0.9998],"evs":[0.0,8.00444]},"44":{"weight":0.4032,"played":[0.0,1.0],"evs":[0.0,7.6872]},"54o":{"weight":0.0,"played":[1.0E-4,0.9999],"evs":[0.0,8.01244]},"64o":{"weight":0.0,"played":[0.0,1.0],"evs":[0.0,6.4766]},"74o":{"weight":0.0,"played":[0.0,1.0],"evs":[0.0,5.82294]},"84o":{"weight":0.0,"played":[0.0,1.0],"evs":[0.0,5.88344]},"94o":{"weight":0.0,"played":[0.0,1.0],"evs":[0.0,3.62938]},"T4o":{"weight":0.0,"played":[0.0,1.0],"evs":[0.0,4.94779]},"J4o":{"weight":0.0,"played":[0.0,1.0],"evs":[0.0,4.79072]},"Q4o":{"weight":0.0,"played":[0.0,1.0],"evs":[0.0,4.73433]},"K4o":{"weight":0.0,"played":[0.0,1.0],"evs":[0.0,4.98114]},"A4o":{"weight":0.0,"played":[0.0,1.0],"evs":[0.0,6.79674]},"52s":{"weight":0.0,"played":[1.0E-4,0.9999],"evs":[0.0,7.4073]},"53s":{"weight":0.0,"played":[2.0E-4,0.9998],"evs":[0.0,7.95347]},"54s":{"weight":0.0,"played":[0.0,1.0],"evs":[0.0,10.5645]},"55":{"weight":0.2348,"played":[0.0,1.0],"evs":[0.0,5.91616]},"65o":{"weight":0.0,"played":[0.0,1.0],"evs":[0.0,7.70894]},"75o":{"weight":0.0,"played":[0.0,1.0],"evs":[0.0,6.9403]},"85o":{"weight":0.0,"played":[0.0,1.0],"evs":[0.0,6.68848]},"95o":{"weight":0.0,"played":[1.0E-4,0.9999],"evs":[0.0,4.93764]},"T5o":{"weight":0.0,"played":[0.0,1.0],"evs":[0.0,3.94018]},"J5o":{"weight":0.0,"played":[0.0,1.0],"evs":[0.0,4.53687]},"Q5o":{"weight":0.0,"played":[1.0E-4,0.9999],"evs":[0.0,5.33333]},"K5o":{"weight":0.0,"played":[0.0,1.0],"evs":[0.0,5.42727]},"A5o":{"weight":0.0,"played":[0.0,1.0],"evs":[0.0,5.85408]},"62s":{"weight":0.0,"played":[0.0,1.0],"evs":[0.0,8.075]},"63s":{"weight":0.0,"played":[0.0,1.0],"evs":[0.0,7.68854]},"64s":{"weight":0.0,"played":[0.0,1.0],"evs":[0.0,9.05531]},"65s":{"weight":0.0,"played":[0.0015,0.9985],"evs":[0.0,9.04605]},"66":{"weight":0.3278,"played":[1.0E-4,0.9999],"evs":[0.0,8.44763]},"76o":{"weight":0.0,"played":[0.0,1.0],"evs":[0.0,7.32621]},"86o":{"weight":0.0,"played":[0.0,1.0],"evs":[0.0,7.17526]},"96o":{"weight":0.0,"played":[0.0,1.0],"evs":[0.0,6.49059]},"T6o":{"weight":0.0,"played":[0.0,1.0],"evs":[0.0,5.22525]},"J6o":{"weight":0.0,"played":[0.0,1.0],"evs":[0.0,5.22196]},"Q6o":{"weight":0.0,"played":[0.0,1.0],"evs":[0.0,5.6971]},"K6o":{"weight":0.0,"played":[0.0,1.0],"evs":[0.0,5.27644]},"A6o":{"weight":0.0,"played":[0.0,1.0],"evs":[0.0,4.82224]},"72s":{"weight":0.0,"played":[0.0071,0.9929],"evs":[0.0,6.87025]},"73s":{"weight":0.0,"played":[8.0E-4,0.9992],"evs":[0.0,6.96283]},"74s":{"weight":0.0,"played":[0.0,1.0],"evs":[0.0,9.15436]},"75s":{"weight":0.0,"played":[0.0,1.0],"evs":[0.0,9.6084]},"76s":{"weight":0.0,"played":[1.0E-4,0.9999],"evs":[0.0,8.77955]},"77":{"weight":0.2939,"played":[0.0,1.0],"evs":[0.0,7.62679]},"87o":{"weight":0.0,"played":[0.0,1.0],"evs":[0.0,7.50331]},"97o":{"weight":0.0,"played":[0.0,1.0],"evs":[0.0,7.05596]},"T7o":{"weight":0.0,"played":[0.0,1.0],"evs":[0.0,6.48236]},"J7o":{"weight":0.0,"played":[0.0,1.0],"evs":[0.0,5.32819]},"Q7o":{"weight":0.0,"played":[0.0,1.0],"evs":[0.0,5.59838]},"K7o":{"weight":0.0,"played":[0.0,1.0],"evs":[0.0,5.01592]},"A7o":{"weight":0.0,"played":[0.0,1.0],"evs":[0.0,5.56042]},"82s":{"weight":0.0,"played":[1.0E-4,0.9999],"evs":[0.0,5.25066]},"83s":{"weight":0.0,"played":[1.0E-4,0.9999],"evs":[0.0,7.07255]},"84s":{"weight":0.0,"played":[1.0E-4,0.9999],"evs":[0.0,7.65904]},"85s":{"weight":0.0,"played":[2.0E-4,0.9998],"evs":[0.0,9.12427]},"86s":{"weight":0.0,"played":[4.0E-4,0.9996],"evs":[0.0,7.50572]},"87s":{"weight":0.0,"played":[0.0,1.0],"evs":[0.0,8.94851]},"88":{"weight":0.494,"played":[0.0,1.0],"evs":[0.0,8.90092]},"98o":{"weight":0.0,"played":[1.0E-4,0.9999],"evs":[0.0,6.78058]},"T8o":{"weight":0.0,"played":[0.0,1.0],"evs":[0.0,7.15847]},"J8o":{"weight":0.0,"played":[0.0,1.0],"evs":[0.0,6.00835]},"Q8o":{"weight":0.0,"played":[0.0,1.0],"evs":[0.0,5.81917]},"K8o":{"weight":0.0,"played":[0.0,1.0],"evs":[0.0,4.95834]},"A8o":{"weight":0.0,"played":[0.0,1.0],"evs":[0.0,5.43775]},"92s":{"weight":0.0,"played":[1.0E-4,0.9999],"evs":[0.0,6.49092]},"93s":{"weight":0.0,"played":[0.0011,0.9989],"evs":[0.0,6.8064]},"94s":{"weight":0.0,"played":[3.0E-4,0.9997],"evs":[0.0,6.95426]},"95s":{"weight":0.0,"played":[0.0,1.0],"evs":[0.0,7.25864]},"96s":{"weight":0.0,"played":[1.0E-4,0.9999],"evs":[0.0,8.29777]},"97s":{"weight":0.0,"played":[1.0E-4,0.9999],"evs":[0.0,9.86925]},"98s":{"weight":0.0,"played":[0.0,1.0],"evs":[0.0,8.56799]},"99":{"weight":0.1949,"played":[0.0,1.0],"evs":[0.0,6.23759]},"T9o":{"weight":0.0,"played":[0.0,1.0],"evs":[0.0,6.48202]},"J9o":{"weight":0.0,"played":[0.0,1.0],"evs":[0.0,6.27908]},"Q9o":{"weight":0.0,"played":[2.0E-4,0.9998],"evs":[0.0,5.49563]},"K9o":{"weight":0.0,"played":[0.0,1.0],"evs":[0.0,5.08105]},"A9o":{"weight":0.2788,"played":[0.0,1.0],"evs":[0.0,4.94003]},"T2s":{"weight":0.0,"played":[5.0E-4,0.9995],"evs":[0.0,5.69521]},"T3s":{"weight":0.0,"played":[8.0E-4,0.9992],"evs":[0.0,5.38804]},"T4s":{"weight":0.0,"played":[0.0,1.0],"evs":[0.0,5.3935]},"T5s":{"weight":0.0,"played":[4.0E-4,0.9996],"evs":[0.0,5.28038]},"T6s":{"weight":0.0,"played":[3.0E-4,0.9997],"evs":[0.0,6.4112]},"T7s":{"weight":0.0,"played":[0.0,1.0],"evs":[0.0,9.09306]},"T8s":{"weight":0.0,"played":[0.0,1.0],"evs":[0.0,7.30601]},"T9s":{"weight":0.0,"played":[1.0E-4,0.9999],"evs":[0.0,7.46862]},"TT":{"weight":0.384,"played":[0.0,1.0],"evs":[0.0,10.67587]},"JTo":{"weight":0.0,"played":[0.0,1.0],"evs":[0.0,6.56396]},"QTo":{"weight":0.0,"played":[0.0,1.0],"evs":[0.0,5.47122]},"KTo":{"weight":0.0,"played":[0.0,1.0],"evs":[0.0,5.90349]},"ATo":{"weight":0.3405,"played":[0.0,1.0],"evs":[0.0,6.19775]},"J2s":{"weight":0.0,"played":[0.0,1.0],"evs":[0.0,5.89055]},"J3s":{"weight":0.0,"played":[0.0,1.0],"evs":[0.0,6.75461]},"J4s":{"weight":0.0,"played":[1.0E-4,0.9999],"evs":[0.0,5.83558]},"J5s":{"weight":0.0,"played":[2.0E-4,0.9998],"evs":[0.0,6.97032]},"J6s":{"weight":0.0,"played":[0.0,1.0],"evs":[0.0,7.12726]},"J7s":{"weight":0.0,"played":[0.0,1.0],"evs":[0.0,7.32099]},"J8s":{"weight":0.0,"played":[6.0E-4,0.9994],"evs":[0.0,10.41356]},"J9s":{"weight":0.0,"played":[0.0016,0.9984],"evs":[0.0,7.90974]},"JTs":{"weight":0.0,"played":[1.0E-4,0.9999],"evs":[0.0,9.87316]},"JJ":{"weight":0.1726,"played":[0.0,1.0],"evs":[0.0,11.11133]},"QJo":{"weight":0.0,"played":[0.0,1.0],"evs":[0.0,6.534]},"KJo":{"weight":0.0,"played":[0.0,1.0],"evs":[0.0,5.50642]},"AJo":{"weight":0.1488,"played":[0.0,1.0],"evs":[0.0,6.36672]},"Q2s":{"weight":0.0,"played":[0.0,1.0],"evs":[0.0,7.28629]},"Q3s":{"weight":0.0,"played":[1.0E-4,0.9999],"evs":[0.0,4.9782]},"Q4s":{"weight":0.0,"played":[1.0E-4,0.9999],"evs":[0.0,8.40083]},"Q5s":{"weight":0.0,"played":[0.0,1.0],"evs":[0.0,8.55997]},"Q6s":{"weight":0.0,"played":[0.0,1.0],"evs":[0.0,6.695]},"Q7s":{"weight":0.0,"played":[0.0,1.0],"evs":[0.0,9.35468]},"Q8s":{"weight":0.0,"played":[4.0E-4,0.9996],"evs":[0.0,6.52404]},"Q9s":{"weight":0.0,"played":[3.0E-4,0.9997],"evs":[0.0,6.49335]},"QTs":{"weight":0.0,"played":[0.0,1.0],"evs":[0.0,8.19525]},"QJs":{"weight":0.0,"played":[1.0E-4,0.9999],"evs":[0.0,8.36058]},"QQ":{"weight":0.1564,"played":[0.0,1.0],"evs":[0.0,12.7541]},"KQo":{"weight":0.4104,"played":[0.0,1.0],"evs":[0.0,7.14648]},"AQo":{"weight":0.2389,"played":[0.0,1.0],"evs":[0.0,7.15273]},"K2s":{"weight":0.0,"played":[5.0E-4,0.9995],"evs":[0.0,8.97779]},"K3s":{"weight":0.0,"played":[1.0E-4,0.9999],"evs":[0.0,6.73973]},"K4s":{"weight":0.0,"played":[1.0E-4,0.9999],"evs":[0.0,6.8605]},"K5s":{"weight":0.0,"played":[0.0046,0.9954],"evs":[0.0,8.31004]},"K6s":{"weight":0.0,"played":[0.0,1.0],"evs":[0.0,8.64169]},"K7s":{"weight":0.0,"played":[0.0,1.0],"evs":[0.0,8.54179]},"K8s":{"weight":0.0,"played":[2.0E-4,0.9998],"evs":[0.0,7.0371]},"K9s":{"weight":0.0,"played":[0.0,1.0],"evs":[0.0,7.68234]},"KTs":{"weight":0.0,"played":[0.0,1.0],"evs":[0.0,6.49369]},"KJs":{"weight":0.3201,"played":[0.0,1.0],"evs":[0.0,7.41666]},"KQs":{"weight":0.1229,"played":[0.0,1.0],"evs":[0.0,9.10269]},"KK":{"weight":0.4908,"played":[0.0,1.0],"evs":[0.0,20.45403]},"AKo":{"weight":0.1943,"played":[0.0,1.0],"evs":[0.0,10.95069]},"A2s":{"weight":0.0,"played":[0.0,1.0],"evs":[0.0,5.74445]},"A3s":{"weight":0.0,"played":[5.0E-4,0.9995],"evs":[0.0,8.38401]},"A4s":{"weight":0.0,"played":[0.0038,0.9962],"evs":[0.0,7.72304]},"A5s":{"weight":0.0,"played":[0.0,1.0],"evs":[0.0,6.29547]},"A6s":{"weight":0.0,"played":[0.0,1.0],"evs":[0.0,7.3073]},"A7s":{"weight":0.0035,"played":[4.0E-4,0.9996],"evs":[0.0,8.18602]},"A8s":{"weight":0.3799,"played":[0.0,1.0],"evs":[0.0,7.56884]},"A9s":{"weight":0.7725,"played":[0.0,1.0],"evs":[0.0,5.48748]},"ATs":{"weight":0.6077,"played":[0.0,1.0],"evs":[0.0,8.69611]},"AJs":{"weight":0.7713,"played":[6.0E-4,0.9994],"evs":[0.0,7.67323]},"AQs":{"weight":0.657,"played":[0.0,1.0],"evs":[0.0,8.87047]},"AKs":{"weight":0.8927,"played":[1.0E-4,0.9999],"evs":[0.0,10.43006]},"AA":{"weight":0.5074,"played":[0.0,1.0],"evs":[0.0,25.71932]}}}