{"player":4,"street":0,"children":2,"sequence":[{"player":0,"type":"F","amount":0,"street":0},{"player":1,"type":"F","amount":0,"street":0},{"player":2,"type":"R","amount":2970000,"street":0},{"player":3,"type":"C","amount":2970000,"street":0}],"actions":[{"type":"F","amount":0,"node":26},{"type":"C","amount":1610000,"node":28}],"hands":{"22":{"weight":1.0,"played":[1.0,0.0],"evs":[0.0,-0.97674]},"32o":{"weight":1.0,"played":[1.0,0.0],"evs":[0.0,-2.54243]},"42o":{"weight":1.0,"played":[1.0,0.0],"evs":[0.0,-2.41774]},"52o":{"weight":1.0,"played":[1.0,0.0],"evs":[0.0,-2.28418]},"62o":{"weight":1.0,"played":[1.0,0.0],"evs":[0.0,-2.45712]},"72o":{"weight":1.0,"played":[1.0,0.0],"evs":[0.0,-2.71084]},"82o":{"weight":1.0,"played":[1.0,0.0],"evs":[0.0,-2.59047]},"92o":{"weight":1.0,"played":[1.0,0.0],"evs":[0.0,-2.58509]},"T2o":{"weight":1.0,"played":[1.0,0.0],"evs":[0.0,-2.44095]},"J2o":{"weight":1.0,"played":[1.0,0.0],"evs":[0.0,-2.48648]},"Q2o":{"weight":1.0,"played":[1.0,0.0],"evs":[0.0,-2.28007]},"K2o":{"weight":1.0,"played":[1.0,0.0],"evs":[0.0,-2.22919]},"A2o":{"weight":1.0,"played":[1.0,0.0],"evs":[0.0,-1.98038]},"32s":{"weight":1.0,"played":[1.0,0.0],"evs":[0.0,-1.75792]},"33":{"weight":1.0,"played":[1.0,0.0],"evs":[0.0,-0.71632]},"43o":{"weight":1.0,"played":[1.0,0.0],"evs":[0.0,-2.10218]},"53o":{"weight":1.0,"played":[1.0,0.0],"evs":[0.0,-1.9725]},"63o":{"weight":1.0,"played":[1.0,0.0],"evs":[0.0,-2.1623]},"73o":{"weight":1.0,"played":[1.0,0.0],"evs":[0.0,-2.43711]},"83o":{"weight":1.0,"played":[1.0,0.0],"evs":[0.0,-2.59133]},"93o":{"weight":1.0,"played":[1.0,0.0],"evs":[0.0,-2.51126]},"T3o":{"weight":1.0,"played":[1.0,0.0],"evs":[0.0,-2.349]},"J3o":{"weight":1.0,"played":[1.0,0.0],"evs":[0.0,-2.41215]},"Q3o":{"weight":1.0,"played":[1.0,0.0],"evs":[0.0,-2.20289]},"K3o":{"weight":1.0,"played":[1.0,0.0],"evs":[0.0,-2.11734]},"A3o":{"weight":1.0,"played":[1.0,0.0],"evs":[0.0,-1.86612]},"42s":{"weight":1.0,"played":[1.0,0.0],"evs":[0.0,-1.69988]},"43s":{"weight":1.0,"played":[1.0,0.0],"evs":[0.0,-1.37848]},"44":{"weight":1.0,"played":[1.0,0.0],"evs":[0.0,-0.41331]},"54o":{"weight":1.0,"played":[1.0,0.0],"evs":[0.0,-1.66711]},"64o":{"weight":1.0,"played":[1.0,0.0],"evs":[0.0,-1.82055]},"74o":{"weight":1.0,"played":[1.0,0.0],"evs":[0.0,-2.09652]},"84o":{"weight":1.0,"played":[1.0,0.0],"evs":[0.0,-2.28054]},"94o":{"weight":1.0,"played":[1.0,0.0],"evs":[0.0,-2.47265]},"T4o":{"weight":1.0,"played":[1.0,0.0],"evs":[0.0,-2.26847]},"J4o":{"weight":1.0,"played":[1.0,0.0],"evs":[0.0,-2.29607]},"Q4o":{"weight":1.0,"played":[1.0,0.0],"evs":[0.0,-2.09295]},"K4o":{"weight":1.0,"played":[1.0,0.0],"evs":[0.0,-2.03123]},"A4o":{"weight":1.0,"played":[1.0,0.0],"evs":[0.0,-1.71588]},"52s":{"weight":1.0,"played":[1.0,0.0],"evs":[0.0,-1.53807]},"53s":{"weight":1.0,"played":[1.0,0.0],"evs":[0.0,-1.23756]},"54s":{"weight":1.0,"played":[1.0,0.0],"evs":[0.0,-0.9821]},"55":{"weight":1.0,"played":[0.9878,0.0122],"evs":[0.0,-0.03987]},"65o":{"weight":1.0,"played":[1.0,0.0],"evs":[0.0,-1.50137]},"75o":{"weight":1.0,"played":[1.0,0.0],"evs":[0.0,-1.74857]},"85o":{"weight":1.0,"played":[1.0,0.0],"evs":[0.0,-1.9134]},"95o":{"weight":1.0,"played":[1.0,0.0],"evs":[0.0,-2.10191]},"T5o":{"weight":1.0,"played":[1.0,0.0],"evs":[0.0,-2.1768]},"J5o":{"weight":1.0,"played":[1.0,0.0],"evs":[0.0,-2.14692]},"Q5o":{"weight":1.0,"played":[1.0,0.0],"evs":[0.0,-1.95302]},"K5o":{"weight":1.0,"played":[1.0,0.0],"evs":[0.0,-1.86294]},"A5o":{"weight":1.0,"played":[1.0,0.0],"evs":[0.0,-1.5055]},"62s":{"weight":1.0,"played":[1.0,0.0],"evs":[0.0,-1.70243]},"63s":{"weight":1.0,"played":[1.0,0.0],"evs":[0.0,-1.4046]},"64s":{"weight":1.0,"played":[1.0,0.0],"evs":[0.0,-1.109]},"65s":{"weight":1.0,"played":[1.0,0.0],"evs":[0.0,-0.80903]},"66":{"weight":1.0,"played":[0.0,1.0],"evs":[0.0,0.22063]},"76o":{"weight":1.0,"played":[1.0,0.0],"evs":[0.0,-1.47279]},"86o":{"weight":1.0,"played":[1.0,0.0],"evs":[0.0,-1.60766]},"96o":{"weight":1.0,"played":[1.0,0.0],"evs":[0.0,-1.79096]},"T6o":{"weight":1.0,"played":[1.0,0.0],"evs":[0.0,-1.86801]},"J6o":{"weight":1.0,"played":[1.0,0.0],"evs":[0.0,-2.09738]},"Q6o":{"weight":1.0,"played":[1.0,0.0],"evs":[0.0,-1.8606]},"K6o":{"weight":1.0,"played":[1.0,0.0],"evs":[0.0,-1.78733]},"A6o":{"weight":1.0,"played":[1.0,0.0],"evs":[0.0,-1.64054]},"72s":{"weight":1.0,"played":[1.0,0.0],"evs":[0.0,-1.96662]},"73s":{"weight":1.0,"played":[1.0,0.0],"evs":[0.0,-1.67793]},"74s":{"weight":1.0,"played":[1.0,0.0],"evs":[0.0,-1.38347]},"75s":{"weight":1.0,"played":[1.0,0.0],"evs":[0.0,-1.07602]},"76s":{"weight":1.0,"played":[1.0,0.0],"evs":[0.0,-0.78273]},"77":{"weight":1.0,"played":[0.0,1.0],"evs":[0.0,0.4357]},"87o":{"weight":1.0,"played":[1.0,0.0],"evs":[0.0,-1.47515]},"97o":{"weight":1.0,"played":[1.0,0.0],"evs":[0.0,-1.61244]},"T7o":{"weight":1.0,"played":[1.0,0.0],"evs":[0.0,-1.70094]},"J7o":{"weight":1.0,"played":[1.0,0.0],"evs":[0.0,-1.96374]},"Q7o":{"weight":1.0,"played":[1.0,0.0],"evs":[0.0,-1.96708]},"K7o":{"weight":1.0,"played":[1.0,0.0],"evs":[0.0,-1.81932]},"A7o":{"weight":1.0,"played":[1.0,0.0],"evs":[0.0,-1.3876]},"82s":{"weight":1.0,"played":[1.0,0.0],"evs":[0.0,-1.86102]},"83s":{"weight":1.0,"played":[1.0,0.0],"evs":[0.0,-1.83144]},"84s":{"weight":1.0,"played":[1.0,0.0],"evs":[0.0,-1.51693]},"85s":{"weight":1.0,"played":[1.0,0.0],"evs":[0.0,-1.18925]},"86s":{"weight":1.0,"played":[1.0,0.0],"evs":[0.0,-0.88189]},"87s":{"weight":1.0,"played":[1.0,0.0],"evs":[0.0,-0.78078]},"88":{"weight":1.0,"played":[0.0,1.0],"evs":[0.0,0.79528]},"98o":{"weight":1.0,"played":[1.0,0.0],"evs":[0.0,-1.39736]},"T8o":{"weight":1.0,"played":[1.0,0.0],"evs":[0.0,-1.43584]},"J8o":{"weight":1.0,"played":[1.0,0.0],"evs":[0.0,-1.6655]},"Q8o":{"weight":1.0,"played":[1.0,0.0],"evs":[0.0,-1.67303]},"K8o":{"weight":1.0,"played":[1.0,0.0],"evs":[0.0,-1.75984]},"A8o":{"weight":1.0,"played":[1.0,0.0],"evs":[0.0,-1.03867]},"92s":{"weight":1.0,"played":[1.0,0.0],"evs":[0.0,-1.83186]},"93s":{"weight":1.0,"played":[1.0,0.0],"evs":[0.0,-1.76043]},"94s":{"weight":1.0,"played":[1.0,0.0],"evs":[0.0,-1.75039]},"95s":{"weight":1.0,"played":[1.0,0.0],"evs":[0.0,-1.37562]},"96s":{"weight":1.0,"played":[1.0,0.0],"evs":[0.0,-1.08574]},"97s":{"weight":1.0,"played":[1.0,0.0],"evs":[0.0,-0.97691]},"98s":{"weight":1.0,"played":[1.0,0.0],"evs":[0.0,-0.70059]},"99":{"weight":1.0,"played":[0.0,1.0],"evs":[0.0,1.22034]},"T9o":{"weight":1.0,"played":[1.0,0.0],"evs":[0.0,-1.19234]},"J9o":{"weight":1.0,"played":[1.0,0.0],"evs":[0.0,-1.36693]},"Q9o":{"weight":1.0,"played":[1.0,0.0],"evs":[0.0,-1.38567]},"K9o":{"weight":1.0,"played":[1.0,0.0],"evs":[0.0,-1.48694]},"A9o":{"weight":1.0,"played":[1.0,0.0],"evs":[0.0,-0.63525]},"T2s":{"weight":1.0,"played":[1.0,0.0],"evs":[0.0,-1.69762]},"T3s":{"weight":1.0,"played":[1.0,0.0],"evs":[0.0,-1.64117]},"T4s":{"weight":1.0,"played":[1.0,0.0],"evs":[0.0,-1.52402]},"T5s":{"weight":1.0,"played":[1.0,0.0],"evs":[0.0,-1.45371]},"T6s":{"weight":1.0,"played":[1.0,0.0],"evs":[0.0,-1.17174]},"T7s":{"weight":1.0,"played":[1.0,0.0],"evs":[0.0,-1.01497]},"T8s":{"weight":1.0,"played":[1.0,0.0],"evs":[0.0,-0.76244]},"T9s":{"weight":1.0,"played":[1.0,0.0],"evs":[0.0,-0.55399]},"TT":{"weight":1.0,"played":[0.0,1.0],"evs":[0.0,1.76865]},"JTo":{"weight":1.0,"played":[1.0,0.0],"evs":[0.0,-0.98359]},"QTo":{"weight":1.0,"played":[1.0,0.0],"evs":[0.0,-0.90085]},"KTo":{"weight":1.0,"played":[1.0,0.0],"evs":[0.0,-0.94446]},"ATo":{"weight":1.0,"played":[0.0,1.0],"evs":[0.0,0.07991]},"J2s":{"weight":1.0,"played":[1.0,0.0],"evs":[0.0,-1.7171]},"J3s":{"weight":1.0,"played":[1.0,0.0],"evs":[0.0,-1.6237]},"J4s":{"weight":1.0,"played":[1.0,0.0],"evs":[0.0,-1.53928]},"J5s":{"weight":1.0,"played":[1.0,0.0],"evs":[0.0,-1.39614]},"J6s":{"weight":1.0,"played":[1.0,0.0],"evs":[0.0,-1.36915]},"J7s":{"weight":1.0,"played":[1.0,0.0],"evs":[0.0,-1.19357]},"J8s":{"weight":1.0,"played":[1.0,0.0],"evs":[0.0,-0.97226]},"J9s":{"weight":1.0,"played":[1.0,0.0],"evs":[0.0,-0.71075]},"JTs":{"weight":1.0,"played":[0.9995,5.0E-4],"evs":[0.0,-0.31859]},"JJ":{"weight":1.0,"played":[0.0,1.0],"evs":[0.0,2.57783]},"QJo":{"weight":1.0,"played":[1.0,0.0],"evs":[0.0,-0.8744]},"KJo":{"weight":1.0,"played":[1.0,0.0],"evs":[0.0,-0.71994]},"AJo":{"weight":1.0,"played":[0.0,1.0],"evs":[0.0,0.5263]},"Q2s":{"weight":1.0,"played":[1.0,0.0],"evs":[0.0,-1.53312]},"Q3s":{"weight":1.0,"played":[1.0,0.0],"evs":[0.0,-1.42269]},"Q4s":{"weight":1.0,"played":[1.0,0.0],"evs":[0.0,-1.34051]},"Q5s":{"weight":1.0,"played":[1.0,0.0],"evs":[0.0,-1.23957]},"Q6s":{"weight":1.0,"played":[1.0,0.0],"evs":[0.0,-1.14533]},"Q7s":{"weight":1.0,"played":[1.0,0.0],"evs":[0.0,-1.21644]},"Q8s":{"weight":1.0,"played":[1.0,0.0],"evs":[0.0,-0.94918]},"Q9s":{"weight":1.0,"played":[1.0,0.0],"evs":[0.0,-0.70935]},"QTs":{"weight":1.0,"played":[1.0,0.0],"evs":[0.0,-0.23754]},"QJs":{"weight":1.0,"played":[1.0,0.0],"evs":[0.0,-0.19534]},"QQ":{"weight":1.0,"played":[0.0,1.0],"evs":[0.0,3.75319]},"KQo":{"weight":1.0,"played":[1.0,0.0],"evs":[0.0,-0.20815]},"AQo":{"weight":1.0,"played":[0.0,1.0],"evs":[0.0,1.12187]},"K2s":{"weight":1.0,"played":[1.0,0.0],"evs":[0.0,-1.43665]},"K3s":{"weight":1.0,"played":[1.0,0.0],"evs":[0.0,-1.38103]},"K4s":{"weight":1.0,"played":[1.0,0.0],"evs":[0.0,-1.27136]},"K5s":{"weight":1.0,"played":[1.0,0.0],"evs":[0.0,-1.13592]},"K6s":{"weight":1.0,"played":[1.0,0.0],"evs":[0.0,-1.03976]},"K7s":{"weight":1.0,"played":[1.0,0.0],"evs":[0.0,-1.08387]},"K8s":{"weight":1.0,"played":[1.0,0.0],"evs":[0.0,-1.03757]},"K9s":{"weight":1.0,"played":[1.0,0.0],"evs":[0.0,-0.76032]},"KTs":{"weight":1.0,"played":[1.0,0.0],"evs":[0.0,-0.25778]},"KJs":{"weight":1.0,"played":[0.2323,0.7677],"evs":[0.0,5.1E-4]},"KQs":{"weight":1.0,"played":[0.0,1.0],"evs":[0.0,0.45212]},"KK":{"weight":1.0,"played":[0.0,1.0],"evs":[0.0,5.23941]},"AKo":{"weight":1.0,"played":[0.0,1.0],"evs":[0.0,1.82435]},"A2s":{"weight":1.0,"played":[1.0,0.0],"evs":[0.0,-1.14131]},"A3s":{"weight":1.0,"played":[1.0,0.0],"evs":[0.0,-1.09199]},"A4s":{"weight":1.0,"played":[1.0,0.0],"evs":[0.0,-0.925]},"A5s":{"weight":1.0,"played":[1.0,0.0],"evs":[0.0,-0.73749]},"A6s":{"weight":1.0,"played":[1.0,0.0],"evs":[0.0,-0.8232]},"A7s":{"weight":1.0,"played":[1.0,0.0],"evs":[0.0,-0.60748]},"A8s":{"weight":1.0,"played":[0.9999,1.0E-4],"evs":[0.0,-0.29371]},"A9s":{"weight":1.0,"played":[3.0E-4,0.9997],"evs":[0.0,0.08509]},"ATs":{"weight":1.0,"played":[0.0,1.0],"evs":[0.0,0.70564]},"AJs":{"weight":1.0,"played":[0.0,1.0],"evs":[0.0,1.18761]},"AQs":{"weight":1.0,"played":[0.0,1.0],"evs":[0.0,1.74913]},"AKs":{"weight":1.0,"played":[0.0,1.0],"evs":[0.0,2.35521]},"AA":{"weight":1.0,"played":[0.0,1.0],"evs":[0.0,7.96823]}}}