{"player":0,"street":0,"children":2,"sequence":[{"player":0,"type":"R","amount":200000,"street":0},{"player":1,"type":"F","amount":0,"street":0},{"player":2,"type":"C","amount":200000,"street":0},{"player":3,"type":"F","amount":0,"street":0},{"player":4,"type":"F","amount":0,"street":0},{"player":5,"type":"R","amount":2165000,"street":0}],"actions":[{"type":"F","amount":0,"node":261},{"type":"C","amount":1965000,"node":262}],"hands":{"22":{"weight":0.0,"played":[0.9999,1.0E-4],"evs":[0.0,-1.60017]},"32o":{"weight":0.0,"played":[1.0,0.0],"evs":[0.0,-7.00249]},"42o":{"weight":0.0,"played":[1.0,0.0],"evs":[0.0,-6.61594]},"52o":{"weight":0.0,"played":[1.0,0.0],"evs":[0.0,-6.72676]},"62o":{"weight":0.0,"played":[1.0,0.0],"evs":[0.0,-7.03825]},"72o":{"weight":0.0,"played":[1.0,0.0],"evs":[0.0,-7.34006]},"82o":{"weight":0.0,"played":[1.0,0.0],"evs":[0.0,-7.14221]},"92o":{"weight":0.0,"played":[1.0,0.0],"evs":[0.0,-6.99563]},"T2o":{"weight":0.0,"played":[1.0,0.0],"evs":[0.0,-6.93672]},"J2o":{"weight":0.0,"played":[1.0,0.0],"evs":[0.0,-6.98359]},"Q2o":{"weight":0.0,"played":[1.0,0.0],"evs":[0.0,-6.46773]},"K2o":{"weight":0.0,"played":[1.0,0.0],"evs":[0.0,-6.41718]},"A2o":{"weight":0.0,"played":[1.0,0.0],"evs":[0.0,-4.88996]},"32s":{"weight":0.0,"played":[1.0,0.0],"evs":[0.0,-5.03237]},"33":{"weight":0.7475,"played":[1.0,0.0],"evs":[0.0,-0.88411]},"43o":{"weight":0.0,"played":[1.0,0.0],"evs":[0.0,-5.84122]},"53o":{"weight":0.0,"played":[1.0,0.0],"evs":[0.0,-5.72603]},"63o":{"weight":0.0,"played":[1.0,0.0],"evs":[0.0,-5.91148]},"73o":{"weight":0.0,"played":[1.0,0.0],"evs":[0.0,-6.59088]},"83o":{"weight":0.0,"played":[1.0,0.0],"evs":[0.0,-7.20534]},"93o":{"weight":0.0,"played":[1.0,0.0],"evs":[0.0,-6.65447]},"T3o":{"weight":0.0,"played":[1.0,0.0],"evs":[0.0,-6.633]},"J3o":{"weight":0.0,"played":[1.0,0.0],"evs":[0.0,-6.71012]},"Q3o":{"weight":0.0,"played":[1.0,0.0],"evs":[0.0,-6.19057]},"K3o":{"weight":0.0,"played":[1.0,0.0],"evs":[0.0,-6.00402]},"A3o":{"weight":0.0,"played":[1.0,0.0],"evs":[0.0,-4.47317]},"42s":{"weight":0.0,"played":[1.0,0.0],"evs":[0.0,-5.25741]},"43s":{"weight":0.0,"played":[1.0,0.0],"evs":[0.0,-4.24831]},"44":{"weight":0.997,"played":[0.9995,5.0E-4],"evs":[0.0,-0.6497]},"54o":{"weight":0.0,"played":[1.0,0.0],"evs":[0.0,-5.64297]},"64o":{"weight":0.0,"played":[1.0,0.0],"evs":[0.0,-5.92699]},"74o":{"weight":0.0,"played":[1.0,0.0],"evs":[0.0,-6.16004]},"84o":{"weight":0.0,"played":[1.0,0.0],"evs":[0.0,-6.30663]},"94o":{"weight":0.0,"played":[1.0,0.0],"evs":[0.0,-6.92547]},"T4o":{"weight":0.0,"played":[1.0,0.0],"evs":[0.0,-6.68705]},"J4o":{"weight":0.0,"played":[1.0,0.0],"evs":[0.0,-6.67973]},"Q4o":{"weight":0.0,"played":[1.0,0.0],"evs":[0.0,-6.15817]},"K4o":{"weight":0.0,"played":[1.0,0.0],"evs":[0.0,-6.08411]},"A4o":{"weight":0.0,"played":[1.0,0.0],"evs":[0.0,-4.84221]},"52s":{"weight":0.0,"played":[1.0,0.0],"evs":[0.0,-5.13144]},"53s":{"weight":0.0,"played":[1.0,0.0],"evs":[0.0,-4.66264]},"54s":{"weight":0.0,"played":[1.0,0.0],"evs":[0.0,-3.89105]},"55":{"weight":0.9391,"played":[0.999,0.001],"evs":[0.0,-0.22461]},"65o":{"weight":0.0,"played":[1.0,0.0],"evs":[0.0,-5.15305]},"75o":{"weight":0.0,"played":[1.0,0.0],"evs":[0.0,-5.37224]},"85o":{"weight":0.0,"played":[1.0,0.0],"evs":[0.0,-6.10383]},"95o":{"weight":0.0,"played":[1.0,0.0],"evs":[0.0,-5.98005]},"T5o":{"weight":0.0,"played":[1.0,0.0],"evs":[0.0,-6.62417]},"J5o":{"weight":0.0,"played":[1.0,0.0],"evs":[0.0,-6.65528]},"Q5o":{"weight":0.0,"played":[1.0,0.0],"evs":[0.0,-5.86195]},"K5o":{"weight":0.0,"played":[1.0,0.0],"evs":[0.0,-5.99862]},"A5o":{"weight":0.0,"played":[1.0,0.0],"evs":[0.0,-4.4016]},"62s":{"weight":0.0,"played":[1.0,0.0],"evs":[0.0,-5.56312]},"63s":{"weight":0.0,"played":[1.0,0.0],"evs":[0.0,-4.93067]},"64s":{"weight":0.0,"played":[1.0,0.0],"evs":[0.0,-4.28314]},"65s":{"weight":0.0,"played":[0.9999,1.0E-4],"evs":[0.0,-3.60306]},"66":{"weight":0.9994,"played":[0.2102,0.7898],"evs":[0.0,0.24862]},"76o":{"weight":0.0,"played":[1.0,0.0],"evs":[0.0,-4.68255]},"86o":{"weight":0.0,"played":[1.0,0.0],"evs":[0.0,-5.14758]},"96o":{"weight":0.0,"played":[1.0,0.0],"evs":[0.0,-5.34964]},"T6o":{"weight":0.0,"played":[1.0,0.0],"evs":[0.0,-5.80087]},"J6o":{"weight":0.0,"played":[1.0,0.0],"evs":[0.0,-6.06175]},"Q6o":{"weight":0.0,"played":[1.0,0.0],"evs":[0.0,-5.5717]},"K6o":{"weight":0.0,"played":[1.0,0.0],"evs":[0.0,-5.47031]},"A6o":{"weight":0.0,"played":[1.0,0.0],"evs":[0.0,-4.41746]},"72s":{"weight":0.0,"played":[1.0,0.0],"evs":[0.0,-5.34636]},"73s":{"weight":0.0,"played":[1.0,0.0],"evs":[0.0,-4.91723]},"74s":{"weight":0.0,"played":[1.0,0.0],"evs":[0.0,-4.519]},"75s":{"weight":0.0,"played":[1.0,0.0],"evs":[0.0,-4.59842]},"76s":{"weight":0.0,"played":[1.0,0.0],"evs":[0.0,-3.42852]},"77":{"weight":0.9025,"played":[0.0062,0.9938],"evs":[0.0,1.64317]},"87o":{"weight":0.0,"played":[1.0,0.0],"evs":[0.0,-4.89181]},"97o":{"weight":0.0,"played":[1.0,0.0],"evs":[0.0,-4.88183]},"T7o":{"weight":0.0,"played":[1.0,0.0],"evs":[0.0,-5.34905]},"J7o":{"weight":0.0,"played":[1.0,0.0],"evs":[0.0,-5.87538]},"Q7o":{"weight":0.0,"played":[1.0,0.0],"evs":[0.0,-5.92233]},"K7o":{"weight":0.0,"played":[1.0,0.0],"evs":[0.0,-5.24186]},"A7o":{"weight":0.0,"played":[1.0,0.0],"evs":[0.0,-3.96083]},"82s":{"weight":0.0,"played":[1.0,0.0],"evs":[0.0,-5.61963]},"83s":{"weight":0.0,"played":[0.9999,1.0E-4],"evs":[0.0,-5.48731]},"84s":{"weight":0.0,"played":[1.0,0.0],"evs":[0.0,-5.09812]},"85s":{"weight":0.0,"played":[1.0,0.0],"evs":[0.0,-4.15062]},"86s":{"weight":0.0,"played":[1.0,0.0],"evs":[0.0,-3.73165]},"87s":{"weight":0.9881,"played":[1.0,0.0],"evs":[0.0,-3.24329]},"88":{"weight":1.0,"played":[0.0,1.0],"evs":[0.0,2.62544]},"98o":{"weight":0.0,"played":[1.0,0.0],"evs":[0.0,-4.43144]},"T8o":{"weight":0.0,"played":[1.0,0.0],"evs":[0.0,-4.7765]},"J8o":{"weight":0.0,"played":[1.0,0.0],"evs":[0.0,-5.16602]},"Q8o":{"weight":0.0,"played":[1.0,0.0],"evs":[0.0,-5.62794]},"K8o":{"weight":0.0,"played":[1.0,0.0],"evs":[0.0,-6.20341]},"A8o":{"weight":0.4191,"played":[1.0,0.0],"evs":[0.0,-3.32996]},"92s":{"weight":0.0,"played":[1.0,0.0],"evs":[0.0,-5.35869]},"93s":{"weight":0.0,"played":[1.0,0.0],"evs":[0.0,-5.29776]},"94s":{"weight":0.0,"played":[1.0,0.0],"evs":[0.0,-5.02275]},"95s":{"weight":0.0,"played":[1.0,0.0],"evs":[0.0,-4.15552]},"96s":{"weight":0.0,"played":[1.0,0.0],"evs":[0.0,-3.57033]},"97s":{"weight":0.0,"played":[1.0,0.0],"evs":[0.0,-3.11664]},"98s":{"weight":1.0,"played":[1.0,0.0],"evs":[0.0,-3.10021]},"99":{"weight":1.0,"played":[0.0,1.0],"evs":[0.0,4.14675]},"T9o":{"weight":0.0,"played":[1.0,0.0],"evs":[0.0,-4.0828]},"J9o":{"weight":0.0,"played":[1.0,0.0],"evs":[0.0,-4.80058]},"Q9o":{"weight":0.0,"played":[1.0,0.0],"evs":[0.0,-4.74365]},"K9o":{"weight":0.0,"played":[1.0,0.0],"evs":[0.0,-5.03991]},"A9o":{"weight":1.0,"played":[1.0,0.0],"evs":[0.0,-1.7811]},"T2s":{"weight":0.0,"played":[1.0,0.0],"evs":[0.0,-5.06114]},"T3s":{"weight":0.0,"played":[1.0,0.0],"evs":[0.0,-5.02559]},"T4s":{"weight":0.0,"played":[1.0,0.0],"evs":[0.0,-5.13003]},"T5s":{"weight":0.0,"played":[1.0,0.0],"evs":[0.0,-4.78723]},"T6s":{"weight":0.0,"played":[1.0,0.0],"evs":[0.0,-3.94929]},"T7s":{"weight":0.0,"played":[1.0,0.0],"evs":[0.0,-3.83417]},"T8s":{"weight":0.9999,"played":[1.0,0.0],"evs":[0.0,-3.21995]},"T9s":{"weight":0.9998,"played":[0.9997,3.0E-4],"evs":[0.0,-2.62694]},"TT":{"weight":1.0,"played":[0.0,1.0],"evs":[0.0,5.78661]},"JTo":{"weight":0.0063,"played":[1.0,0.0],"evs":[0.0,-4.2195]},"QTo":{"weight":0.6069,"played":[1.0,0.0],"evs":[0.0,-3.98855]},"KTo":{"weight":0.9158,"played":[1.0,0.0],"evs":[0.0,-4.25349]},"ATo":{"weight":1.0,"played":[0.8691,0.1309],"evs":[0.0,-0.00708]},"J2s":{"weight":0.0,"played":[1.0,0.0],"evs":[0.0,-4.92781]},"J3s":{"weight":0.0,"played":[1.0,0.0],"evs":[0.0,-4.96461]},"J4s":{"weight":0.0,"played":[1.0,0.0],"evs":[0.0,-5.0321]},"J5s":{"weight":0.0,"played":[1.0,0.0],"evs":[0.0,-4.68336]},"J6s":{"weight":0.0,"played":[1.0,0.0],"evs":[0.0,-4.62548]},"J7s":{"weight":0.0,"played":[1.0,0.0],"evs":[0.0,-3.94057]},"J8s":{"weight":0.6924,"played":[1.0,0.0],"evs":[0.0,-3.48749]},"J9s":{"weight":1.0,"played":[0.9999,1.0E-4],"evs":[0.0,-3.15998]},"JTs":{"weight":0.9864,"played":[0.9999,1.0E-4],"evs":[0.0,-2.74447]},"JJ":{"weight":1.0,"played":[0.0,1.0],"evs":[0.0,6.90541]},"QJo":{"weight":1.0,"played":[1.0,0.0],"evs":[0.0,-3.94243]},"KJo":{"weight":1.0,"played":[1.0,0.0],"evs":[0.0,-4.16589]},"AJo":{"weight":0.8858,"played":[5.0E-4,0.9995],"evs":[0.0,1.45828]},"Q2s":{"weight":0.0,"played":[1.0,0.0],"evs":[0.0,-4.94551]},"Q3s":{"weight":0.0,"played":[1.0,0.0],"evs":[0.0,-4.46778]},"Q4s":{"weight":0.0,"played":[1.0,0.0],"evs":[0.0,-4.65763]},"Q5s":{"weight":0.0,"played":[0.9999,1.0E-4],"evs":[0.0,-4.25996]},"Q6s":{"weight":0.0,"played":[1.0,0.0],"evs":[0.0,-4.19649]},"Q7s":{"weight":0.0,"played":[1.0,0.0],"evs":[0.0,-3.87312]},"Q8s":{"weight":1.0,"played":[1.0,0.0],"evs":[0.0,-3.94831]},"Q9s":{"weight":1.0,"played":[1.0,0.0],"evs":[0.0,-2.99273]},"QTs":{"weight":0.9999,"played":[1.0,0.0],"evs":[0.0,-2.16917]},"QJs":{"weight":1.0,"played":[0.9998,2.0E-4],"evs":[0.0,-2.59851]},"QQ":{"weight":1.0,"played":[0.0,1.0],"evs":[0.0,8.92414]},"KQo":{"weight":0.9767,"played":[1.0,0.0],"evs":[0.0,-2.90831]},"AQo":{"weight":0.9409,"played":[0.0,1.0],"evs":[0.0,3.72198]},"K2s":{"weight":0.0,"played":[0.9999,1.0E-4],"evs":[0.0,-4.56421]},"K3s":{"weight":0.0,"played":[1.0,0.0],"evs":[0.0,-4.72185]},"K4s":{"weight":0.0,"played":[1.0,0.0],"evs":[0.0,-4.74693]},"K5s":{"weight":0.0,"played":[1.0,0.0],"evs":[0.0,-4.30778]},"K6s":{"weight":0.0064,"played":[0.9999,1.0E-4],"evs":[0.0,-4.16479]},"K7s":{"weight":0.9995,"played":[1.0,0.0],"evs":[0.0,-3.89499]},"K8s":{"weight":0.9999,"played":[1.0,0.0],"evs":[0.0,-4.08101]},"K9s":{"weight":1.0,"played":[1.0,0.0],"evs":[0.0,-3.37342]},"KTs":{"weight":0.6444,"played":[0.9999,1.0E-4],"evs":[0.0,-2.78465]},"KJs":{"weight":0.9999,"played":[0.9998,2.0E-4],"evs":[0.0,-2.70694]},"KQs":{"weight":1.0,"played":[0.9994,6.0E-4],"evs":[0.0,-1.536]},"KK":{"weight":1.0,"played":[0.0,1.0],"evs":[0.0,10.78883]},"AKo":{"weight":1.0,"played":[0.0,1.0],"evs":[0.0,5.70361]},"A2s":{"weight":1.0,"played":[1.0,0.0],"evs":[0.0,-3.17273]},"A3s":{"weight":1.0,"played":[0.9999,1.0E-4],"evs":[0.0,-3.12652]},"A4s":{"weight":1.0,"played":[0.9999,1.0E-4],"evs":[0.0,-2.88564]},"A5s":{"weight":1.0,"played":[1.0,0.0],"evs":[0.0,-2.54904]},"A6s":{"weight":1.0,"played":[0.9999,1.0E-4],"evs":[0.0,-3.08305]},"A7s":{"weight":1.0,"played":[1.0,0.0],"evs":[0.0,-2.11682]},"A8s":{"weight":1.0,"played":[0.9999,1.0E-4],"evs":[0.0,-2.19054]},"A9s":{"weight":1.0,"played":[0.9995,5.0E-4],"evs":[0.0,-0.64095]},"ATs":{"weight":1.0,"played":[0.0168,0.9832],"evs":[0.0,1.63732]},"AJs":{"weight":1.0,"played":[0.0,1.0],"evs":[0.0,3.02571]},"AQs":{"weight":1.0,"played":[0.0,1.0],"evs":[0.0,4.87281]},"AKs":{"weight":1.0,"played":[0.0,1.0],"evs":[0.0,6.67887]},"AA":{"weight":1.0,"played":[0.0,1.0],"evs":[0.0,18.01862]}}}